pigpio.py
pigpio-1.46.dist-info/METADATA
pigpio-1.46.dist-info/WHEEL
pigpio-1.46.dist-info/top_level.txt
pigpio-1.46.dist-info/RECORD
