Metadata-Version: 1.2
Name: pigpio
Version: 1.46
Summary: Raspberry Pi GPIO module
Home-page: http://abyz.me.uk/rpi/pigpio/python.html
Author: joan
Author-email: joan@abyz.me.uk
Maintainer: joan
Maintainer-email: joan@abyz.me.uk
License: unlicense.org
Download-URL: http://abyz.me.uk/rpi/pigpio/pigpio.zip
Keywords: raspberrypi,gpio
Platform: UNKNOWN
Classifier: Programming Language :: Python :: 2
Classifier: Programming Language :: Python :: 3
